pynoder
