Metadata-Version: 1.0
Name: pynoder
Version: 1.0.2
Summary: A Python and PyQt5 package for creating a node-based editor.
Home-page: https://github.com/johnroper100/PyNoder
Author: John Roper
Author-email: johnroper100@gmail.com
License: GPL3.0
Platform: UNKNOWN
